ultracart/__init__.py
ultracart/api_client.py
ultracart/configuration.py
ultracart/exceptions.py
ultracart/model_utils.py
ultracart/rest.py
ultracart/api/__init__.py
ultracart/api/affiliate_api.py
ultracart/api/auto_order_api.py
ultracart/api/channel_partner_api.py
ultracart/api/checkout_api.py
ultracart/api/conversation_api.py
ultracart/api/coupon_api.py
ultracart/api/customer_api.py
ultracart/api/datawarehouse_api.py
ultracart/api/fulfillment_api.py
ultracart/api/gift_certificate_api.py
ultracart/api/integration_log_api.py
ultracart/api/item_api.py
ultracart/api/oauth_api.py
ultracart/api/order_api.py
ultracart/api/sso_api.py
ultracart/api/storefront_api.py
ultracart/api/tax_api.py
ultracart/api/user_api.py
ultracart/api/webhook_api.py
ultracart/api/workflow_api.py
ultracart/apis/__init__.py
ultracart/model/__init__.py
ultracart/model/accounts_receivable_retry_config.py
ultracart/model/accounts_receivable_retry_config_response.py
ultracart/model/accounts_receivable_retry_day_activity.py
ultracart/model/accounts_receivable_retry_stat_account.py
ultracart/model/accounts_receivable_retry_stat_metrics.py
ultracart/model/accounts_receivable_retry_stat_revenue.py
ultracart/model/accounts_receivable_retry_stats_response.py
ultracart/model/accounts_receivable_retry_transaction_reject.py
ultracart/model/activity.py
ultracart/model/add_library_item_request.py
ultracart/model/adjust_internal_certificate_request.py
ultracart/model/adjust_internal_certificate_response.py
ultracart/model/affiliate_click.py
ultracart/model/affiliate_click_query.py
ultracart/model/affiliate_clicks_response.py
ultracart/model/affiliate_ledger.py
ultracart/model/affiliate_ledger_query.py
ultracart/model/affiliate_ledgers_response.py
ultracart/model/affiliate_link.py
ultracart/model/api_user_application_profile.py
ultracart/model/apply_library_item_request.py
ultracart/model/apply_library_item_response.py
ultracart/model/auto_order.py
ultracart/model/auto_order_addon_item.py
ultracart_rest_sdk-4.1.51.dist-info/LICENSE
ultracart_rest_sdk-4.1.51.dist-info/METADATA
ultracart_rest_sdk-4.1.51.dist-info/WHEEL
ultracart_rest_sdk-4.1.51.dist-info/top_level.txt
ultracart_rest_sdk-4.1.51.dist-info/RECORD
