Metadata-Version: 2.1
Name: ultracart-rest-sdk
Version: 4.1.51
Summary: UltraCart Rest API V2
Home-page: UNKNOWN
Author: UltraCart Support
Author-email: support@ultracart.com
License: UNKNOWN
Keywords: OpenAPI,OpenAPI-Generator,UltraCart Rest API V2
Platform: UNKNOWN
Requires-Python: >=3.6
Requires-Dist: urllib3 (>=1.25.3)
Requires-Dist: python-dateutil
